zenggewifi/__init__.py
zenggewifi-0.0.3.dist-info/LICENSE
zenggewifi-0.0.3.dist-info/METADATA
zenggewifi-0.0.3.dist-info/WHEEL
zenggewifi-0.0.3.dist-info/top_level.txt
zenggewifi-0.0.3.dist-info/RECORD
