Metadata-Version: 2.1
Name: zenggewifi
Version: 0.0.3
Summary: Communication to Zengge Wifi bulbs
Home-page: https://github.com/autinerd/python-zenggewifi
Author: Sidney Kuyateh
Author-email: sidneyjohn23@icloud.com
License: UNKNOWN
Platform: UNKNOWN
Classifier: Programming Language :: Python :: 3
Classifier: License :: OSI Approved :: GNU General Public License v3 (GPLv3)
Classifier: Operating System :: OS Independent
Classifier: Development Status :: 4 - Beta
Classifier: Intended Audience :: Developers
